{
  "neoforge:conditions": [
    {
      "type": "neoforge:mod_loaded",
      "modid": "modern_industrialization"
    },
    {
      "type": "neoforge:mod_loaded",
      "modid": "allthemodium"
    }
  ],
  "type": "modern_industrialization:implosion_compressor",
  "eu": 1,
  "duration": 10,
  "item_inputs": [
    {
      "tag": "c:dusts/allthemodium",
      "amount": 1
    },
    {
      "item": "modern_industrialization:industrial_tnt",
      "amount": 1
    }
  ],
  "item_outputs": {
    "item": "allthemodium:allthemodium_crystal",
    "amount": 1
  }
}
