{
  "type": "cyclic:crusher",
  "input": {
    "tag": "forge:clumps/unobtainium"
  },
  "energy": {
    "ticks": 1200,
    "rfpertick": 120
  },
  "result": {
    "item": "allthemodium:raw_unobtainium",
    "count": 1
  },

  "conditions": [
    {
      "values": [
        {
          "modid": "cyclic",
          "type": "forge:mod_loaded"
        },
        {
          "modid": "allthemodium",
          "type": "forge:mod_loaded"
        },
        {
          "item": "cyclic:crusher",
          "type": "forge:item_exists"
        },
        {
          "value": {
            "type": "forge:tag_empty",
            "tag": "forge:clumps/unobtainium"
          },
          "type": "forge:not"
        }
      ],
      "type": "forge:and"
    }
  ]
}
